symphony_vega/__init__.py
symphony_vega/_frontend.py
symphony_vega/_version.py
symphony_vega/widget.py
symphony_vega/labextension/build_log.json
symphony_vega/labextension/package.json
symphony_vega/labextension/static/lib_index_js.8e8e94900732b6b25b8e.js
symphony_vega/labextension/static/lib_index_js.8e8e94900732b6b25b8e.js.map
symphony_vega/labextension/static/lib_index_js.d9834959f71dff7b05f1.js
symphony_vega/labextension/static/lib_index_js.d9834959f71dff7b05f1.js.map
symphony_vega/labextension/static/remoteEntry.4a6ac3ae49919e74e936.js
symphony_vega/labextension/static/remoteEntry.4a6ac3ae49919e74e936.js.map
symphony_vega/labextension/static/remoteEntry.8d04f5e82ce319b7438f.js
symphony_vega/labextension/static/remoteEntry.8d04f5e82ce319b7438f.js.map
symphony_vega/labextension/static/style.js
symphony_vega/nbextension/extension.js
symphony_vega/nbextension/index.js
symphony_vega/standalone/widgets/SymphonyVega.js
symphony_vega/standalone/widgets/SymphonyVega.js.map
symphony_vega-1.0.2.data/data/etc/jupyter/nbconfig/notebook.d/symphony_vega.json
symphony_vega-1.0.2.data/data/share/jupyter/labextensions/symphony-vega/build_log.json
symphony_vega-1.0.2.data/data/share/jupyter/labextensions/symphony-vega/install.json
symphony_vega-1.0.2.data/data/share/jupyter/labextensions/symphony-vega/package.json
symphony_vega-1.0.2.data/data/share/jupyter/labextensions/symphony-vega/static/lib_index_js.8e8e94900732b6b25b8e.js
symphony_vega-1.0.2.data/data/share/jupyter/labextensions/symphony-vega/static/lib_index_js.8e8e94900732b6b25b8e.js.map
symphony_vega-1.0.2.data/data/share/jupyter/labextensions/symphony-vega/static/remoteEntry.8d04f5e82ce319b7438f.js
symphony_vega-1.0.2.data/data/share/jupyter/labextensions/symphony-vega/static/remoteEntry.8d04f5e82ce319b7438f.js.map
symphony_vega-1.0.2.data/data/share/jupyter/labextensions/symphony-vega/static/style.js
symphony_vega-1.0.2.data/data/share/jupyter/nbextensions/symphony_vega/extension.js
symphony_vega-1.0.2.dist-info/LICENSE.txt
symphony_vega-1.0.2.dist-info/METADATA
symphony_vega-1.0.2.dist-info/WHEEL
symphony_vega-1.0.2.dist-info/top_level.txt
symphony_vega-1.0.2.dist-info/RECORD
